kikiutils_base/__init__.py
kikiutils_base/check.py
kikiutils_base/file.py
kikiutils_base/import_utils.py
kikiutils_base/json.py
kikiutils_base/log.py
kikiutils_base/number.py
kikiutils_base/string.py
kikiutils_base/time.py
kikiutils_base/url.py
kiki_utils_base-1.0.0.dist-info/LICENSE.txt
kiki_utils_base-1.0.0.dist-info/METADATA
kiki_utils_base-1.0.0.dist-info/WHEEL
kiki_utils_base-1.0.0.dist-info/top_level.txt
kiki_utils_base-1.0.0.dist-info/zip-safe
kiki_utils_base-1.0.0.dist-info/RECORD
