Metadata-Version: 2.1
Name: kiki-utils-base
Version: 1.0.0
Summary: Utils functions without other packages
Author: kiki-kanri
Author-email: a470666@gmail.com
Keywords: Utils
Classifier: License :: Freely Distributable
Requires-Python: >=3.6
License-File: LICENSE.txt
Requires-Dist: loguru
